{
    "format_version": "1.8.0",
    "animations": {
        "animation.harpoon_gun.third_person_main_hand": {
            "loop": true,
            "bones": {
                "root": {
                    "position": [ 0, 11, -4],
                    "rotation": [ 90, 0, 0],
                    "scale": [ 0.9, 0.9, 0.9]
                }
            }
        },
        "animation.harpoon_gun.first_person_main_hand": {
            "loop": true,
            "bones": {
                "root": {
                    "position": [ 0, 10, 0],
                    "rotation": [ 90, 60, -50],
                    "scale": [ 0.9, 0.9, 0.9]                
                }
            }
        }
    }
}